<?xml version='1.0' encoding='SHIFT_JIS'?>
<Root>
  <isBigEndian Value="False"/>
  <BymlFormatVersion Value="3"/>
  <C1>
    <C1 Name="ActorParams">
      <D1 Name="mJumpFrame" StringValue="150"/>
      <D1 Name="mAttackNum" StringValue="2"/>
      <D2 Name="mShotTargetHeight" StringValue="50"/>
      <D0 Name="mIsEnablePassClosePath" StringValue="True"/>
      <D2 Name="mActionSpeedMax" StringValue="3"/>
      <D2 Name="mGndColOffsetY" StringValue="0"/>
      <C0 Name="mSuperMissileTargetPosOffset">
        <D2 StringValue="0"/>
        <D2 StringValue="0"/>
        <D2 StringValue="0"/>
      </C0>
      <D0 Name="mCheckKeepOutE" StringValue="False"/>
      <D0 Name="mIsDroppable" StringValue="True"/>
      <D2 Name="mShotDegAxisY" StringValue="25"/>
      <D0 Name="mmLifeCure" StringValue="False"/>
      <D2 Name="mBulletDistanceSlow" StringValue="30"/>
      <C1 Name="mSearchableParams">
        <A0 Name="40071f38" StringValue="cPathDistance"/>
        <D0 Name="mIsCheckCol" StringValue="False"/>
      </C1>
      <D2 Name="mArrivalPointDistanceMin" StringValue="200"/>
      <D2 Name="mOffsetY_InWater" StringValue="-10"/>
      <C1 Name="mPathPlannableParams">
        <D0 Name="mEnableCoopAreaKeepOut" StringValue="False"/>
        <D2 Name="mReachDistanceXZ" StringValue="20"/>
        <D2 Name="mReachDistanceY" StringValue="20"/>
        <D0 Name="mEnableReachTarget" StringValue="True"/>
      </C1>
      <D1 Name="mLife" StringValue="9000"/>
      <C0 Name="mAirBallPosOffset">
        <D2 StringValue="0"/>
        <D2 StringValue="0"/>
        <D2 StringValue="0"/>
      </C0>
      <D2 Name="mDiePaintRadius" StringValue="80"/>
      <C1 Name="mEnemyPhysicsParams">
        <C1 Name="mObjColCapsuleParams">
          <C1 Name="mObjColCapsuleParams[1]">
            <A0 Name="mArmorType" StringValue="cZakoEnemy"/>
            <D2 Name="mHeight" StringValue="0"/>
            <C0 Name="mOffset">
              <D2 StringValue="0"/>
              <D2 StringValue="-1.5"/>
              <D2 StringValue="0"/>
            </C0>
            <D0 Name="mUseOwnerMtx" StringValue="False"/>
            <C0 Name="mRotate">
              <D2 StringValue="0"/>
              <D2 StringValue="0"/>
              <D2 StringValue="0"/>
            </C0>
            <D2 Name="mRadius" StringValue="18"/>
            <A0 Name="mNodeName" StringValue="Salmon_Joint_Root"/>
            <D0 Name="mIsBombBreak" StringValue="False"/>
          </C1>
          <C1 Name="mObjColCapsuleParams[0]">
            <A0 Name="mArmorType" StringValue="cEnemyShield"/>
            <D2 Name="mHeight" StringValue="0"/>
            <C0 Name="mOffset">
              <D2 StringValue="0"/>
              <D2 StringValue="-5"/>
              <D2 StringValue="0"/>
            </C0>
            <D0 Name="mUseOwnerMtx" StringValue="False"/>
            <C0 Name="mRotate">
              <D2 StringValue="0"/>
              <D2 StringValue="0"/>
              <D2 StringValue="0"/>
            </C0>
            <D2 Name="mRadius" StringValue="15"/>
            <A0 Name="mNodeName" StringValue="Umb_transY"/>
            <D0 Name="mIsBombBreak" StringValue="False"/>
          </C1>
        </C1>
        <D2 Name="mGndColRadius" StringValue="10"/>
        <D0 Name="mIsKeepoutEReject" StringValue="True"/>
        <D0 Name="mIsKeepoutE2Reject" StringValue="False"/>
        <C0 Name="mGndColOffset">
          <D2 StringValue="0"/>
          <D2 StringValue="0"/>
          <D2 StringValue="0"/>
        </C0>
      </C1>
      <D1 Name="mmLifeCurePerSecond" StringValue="100"/>
      <D2 Name="mKnockbackRollerCore" StringValue="1"/>
      <D2 Name="mTrackPaintableRadius" StringValue="32"/>
      <D2 Name="mScale" StringValue="1"/>
      <D2 Name="mWeight" StringValue="7"/>
      <D2 Name="mDieSplashRadius" StringValue="80"/>
      <A0 Name="mAnimNameWaitSpawn" StringValue="Wait00"/>
      <D2 Name="mSearchBombSearchPosOffsetY" StringValue="0"/>
      <D2 Name="mFootPaintCheckThreshold" StringValue="0.33"/>
      <D2 Name="mAttackRangeXZ" StringValue="300"/>
      <D2 Name="mBulletDistanceFast" StringValue="150"/>
    </C1>
  </C1>
</Root>