{
  "mBurst_SplashPaintR": 7,
  "mBurst_SplashVelL": 5.2,
  "mBurst_KnockBackCoreImpact": 2,
  "mBurst_SplashNum": 10,
  "mBurst_SplashOfstY": 3,
  "mCrossPaintRadius": 14,
  "mBurst_SplashPitH": 30,
  "mBurst_Radius_Middle": 32,
  "mBurst_Damage_Far": 250,
  "mShape_SphereR": 2,
  "mBurst_Damage_Near": 350,
  "mFly_RotKd": 0.98015,
  "mFly_InitPit": 0.4,
  "mBringCloseRateMoveVec": 0.7,
  "mBurst_Radius_Near": 32,
  "mBurst_KnockBackKb": 0.8,
  "mBurst_SplashAroundFuzzyRate": 2,
  "mFly_InitRol": 0.12,
  "mEffectShakeRange": 70,
  "mFly_Gravity": 0.16,
  "mBombDamage": 250,
  "mCrossPaintRayRadius": 1,
  "mInkConsume": 0.4,
  "mBurst_KnockBackRadius": 80,
  "mShape_SphereD": 5,
  "mBurst_SplashPitL": 5,
  "mBurst_SplashVelH": 3.5,
  "mBurst_Damage_Middle": 350,
  "mBringCloseRateCrossVec": 0.7,
  "mBurst_Radius_Far": 40,
  "mBurst_PaintR": 40,
  "mCrossPaintRayLength": 14,
  "mFly_RotI": 20,
  "mFly_VelKd": 0.941337
}